{
  "blogs": [
    {
      "id": 1,
      "title": "Introduction to JavaScript",
      "content": "JavaScript is a programming language...",
      "imageUrl": "https://www.orientsoftware.com/Themes/OrientSoftwareTheme/Content/Images/blog/2021-12-16/what-can-you-do-with-javascript-thumb.jpg",
      "author": "John Doe"
    },
    {
      "id": 2,
      "title": "Getting Started with React",
      "content": "React is a JavaScript library...",
      "imageUrl": "https://miro.medium.com/v2/resize:fit:2000/1*y6C4nSvy2Woe0m7bWEn4BA.png",
      "author": "Jane Smith"
    },
    {
      "id": 3,
      "title": "Python Basics",
      "content": "Python is an interpreted, high-level programming language...",
      "imageUrl": "https://miro.medium.com/v2/resize:fit:1400/1*ycIMlwgwicqlO6PcFRA-Iw.png",
      "author": "Alex Johnson"
    }
  ],
  "users" :[
    {
      "username": "fazaamal",
      "name": "Faza Amal",
      "password": "123456"
    }
  ]
    
}
